[
    {
        "imdb_id": "nm0474774",
        "name": "Akshay Kumar"
    },
    {
        "imdb_id": "nm1909661",
        "name": "Nimrat Kaur"
    },
    {
        "imdb_id": "nm1122912",
        "name": "Kumud Mishra"
    },
    {
        "imdb_id": "nm5787869",
        "name": "Prakash Belawadi"
    },
    {
        "imdb_id": "nm4189429",
        "name": "Inaamulhaq"
    },
    {
        "imdb_id": "nm2445419",
        "name": "Lena"
    },
    {
        "imdb_id": "nm0451281",
        "name": "Nissar Khan"
    },
    {
        "imdb_id": "nm1011408",
        "name": "Ninad Kamat"
    },
    {
        "imdb_id": "nm0467868",
        "name": "Kaizaad Kotwal"
    },
    {
        "imdb_id": "nm3092039",
        "name": "Feryna Wazheir"
    },
    {
        "imdb_id": "nm6455556",
        "name": "Ajay Kumar"
    },
    {
        "imdb_id": "nm1327322",
        "name": "Purab Kohli"
    },
    {
        "imdb_id": "nm7178571",
        "name": "Gunjan Malhotra"
    },
    {
        "imdb_id": "nm6845053",
        "name": "Pooja Nair"
    },
    {
        "imdb_id": "nm2712038",
        "name": "Taranjit Kaur"
    },
    {
        "imdb_id": "nm8379639",
        "name": "Ajay Arya"
    },
    {
        "imdb_id": "nm0318622",
        "name": "Avtar Gill"
    },
    {
        "imdb_id": "nm1428293",
        "name": "Pawan Chopra"
    },
    {
        "imdb_id": "nm0050187",
        "name": "Arun Bali"
    },
    {
        "imdb_id": "nm0657184",
        "name": "Surendra Pal"
    },
    {
        "imdb_id": "nm7874596",
        "name": "Adiba Hussain"
    },
    {
        "imdb_id": "nm8379640",
        "name": "Ritika Badiani"
    },
    {
        "imdb_id": "nm8379641",
        "name": "Tvisha Bhavin Chopra"
    },
    {
        "imdb_id": "nm8379642",
        "name": "Jiyaara Pitalia"
    },
    {
        "imdb_id": "nm8379643",
        "name": "Masood Ahmed"
    },
    {
        "imdb_id": "nm8379644",
        "name": "Kamal Karamchandani"
    },
    {
        "imdb_id": "nm8379645",
        "name": "Jashan Singh Kohli"
    },
    {
        "imdb_id": "nm3166643",
        "name": "Jennifer Mistry Bansiwal"
    },
    {
        "imdb_id": "nm1586516",
        "name": "Bachan Pachehra"
    },
    {
        "imdb_id": "nm8146462",
        "name": "Harshad Kumar"
    },
    {
        "imdb_id": "nm7818532",
        "name": "Ahtesham Hussain"
    },
    {
        "imdb_id": "nm8379647",
        "name": "M.G. Radhakrishnana"
    },
    {
        "imdb_id": "nm8379648",
        "name": "Ruby Kushwah"
    },
    {
        "imdb_id": "nm3054406",
        "name": "Jaiveer"
    },
    {
        "imdb_id": "nm7928893",
        "name": "Kapil Punjabi"
    },
    {
        "imdb_id": "nm8379649",
        "name": "Uday Bhardwaj"
    },
    {
        "imdb_id": "nm1616785",
        "name": "Rajesh Jais"
    },
    {
        "imdb_id": "nm1693210",
        "name": "Sanjay Bhatia"
    },
    {
        "imdb_id": "nm7545875",
        "name": "Abhijit Bhor"
    },
    {
        "imdb_id": "nm4718913",
        "name": "Aaradhna Uppal"
    },
    {
        "imdb_id": "nm5650997",
        "name": "Shekhar Shukla"
    },
    {
        "imdb_id": "nm4366664",
        "name": "Narendra Jetley"
    },
    {
        "imdb_id": "nm4113243",
        "name": "Karim Hajee"
    },
    {
        "imdb_id": "nm8719360",
        "name": "Parveen Kaur"
    },
    {
        "imdb_id": "nm6040403",
        "name": "Sameer Ali Khan"
    },
    {
        "imdb_id": "nm7648624",
        "name": "Ratnesh Mani"
    },
    {
        "imdb_id": "nm4316542",
        "name": "Udai Singh Pawar"
    },
    {
        "imdb_id": "nm8475179",
        "name": "Rockey Raina"
    },
    {
        "imdb_id": "nm6710445",
        "name": "Satya Ranjan"
    },
    {
        "imdb_id": "nm1252093",
        "name": "Robert Lang"
    }
]