{
    "Bio": "Ramanujam, who suffers from multiple personality disorder, works as a lawyer by day and a vigilante at night. He uses tips from the 'Garuda Purana' as his tools to expose various antisocial elements.",
    "Country": "India",
    "Director": [
        "S. Shankar"
    ],
    "Genres": [
        " Action",
        " Drama",
        " Thriller"
    ],
    "Language": [
        "Tamil",
        "Telugu",
        "French",
        "Hindi"
    ],
    "Name": "Anniyan",
    "Poster URL": "https://m.media-amazon.com/images/M/MV5BMDNjMWIxMTEtMDU0MS00NDAyLThhN2YtNmFjMzViZWYxZjllXkEyXkFqcGdeQXVyNTgyNTA4MjM@._V1_UY268_CR0,0,182,268_AL__QL50.jpg",
    "Runtime": "181 min"
}